fiducia_miner/__init__.py
fiducia_miner/cli.py
fiducia_miner/miner.py
fiducia_miner-1.0.0.dist-info/LICENSE
fiducia_miner-1.0.0.dist-info/METADATA
fiducia_miner-1.0.0.dist-info/WHEEL
fiducia_miner-1.0.0.dist-info/entry_points.txt
fiducia_miner-1.0.0.dist-info/top_level.txt
fiducia_miner-1.0.0.dist-info/RECORD
