Metadata-Version: 2.1
Name: fiducia-miner
Version: 1.0.0
Summary: A mining client for Fiducia blockchain
Home-page: https://github.com/yourusername/fiducia-miner
Author: Fiducia Team
Author-email: info@fiducia.org
Classifier: Programming Language :: Python :: 3
Classifier: License :: OSI Approved :: MIT License
Classifier: Operating System :: OS Independent
Requires-Python: >=3.6
License-File: LICENSE
Requires-Dist: argparse
